aivibe/__init__.py
aivibe/cli.py
aivibe/evaluator.py
aivibe/models.py
aivibe/scheduler.py
aivibe/trainer.py
aivibe/knowledge/__init__.py
aivibe/knowledge/aws.py
aivibe/knowledge/dart.py
aivibe/knowledge/firebase.py
aivibe/knowledge/flutter.py
aivibe/knowledge/gcloud.py
aivibe/knowledge/javascript.py
aivibe/knowledge/kotlin.py
aivibe/knowledge/postgresql.py
aivibe/knowledge/python.py
aivibe/knowledge/sdlc.py
aivibe/knowledge/troubleshooting.py
aivibe-1.0.1.dist-info/METADATA
aivibe-1.0.1.dist-info/WHEEL
aivibe-1.0.1.dist-info/entry_points.txt
aivibe-1.0.1.dist-info/top_level.txt
aivibe-1.0.1.dist-info/RECORD
