Metadata-Version: 2.4
Name: aivibe
Version: 1.0.1
Summary: AI Vibe - Complete AI Agent Training Package for VibeKaro.ai Platform with Flutter, Dart, Kotlin, Python, AWS expertise
Author-email: AICippy Technologies <dev@vibekaro.ai>
Maintainer-email: VibeKaro AI Team <support@vibekaro.ai>
License: MIT
Project-URL: Homepage, https://vibekaro.ai
Project-URL: Documentation, https://docs.vibekaro.ai
Project-URL: Repository, https://github.com/aicippy/aivibe
Project-URL: Issues, https://github.com/aicippy/aivibe/issues
Keywords: ai,agent,training,flutter,dart,kotlin,python,aws,gcloud,firebase,sdlc,coding-standards,vibekaro
Classifier: Development Status :: 5 - Production/Stable
Classifier: Intended Audience :: Developers
Classifier: License :: OSI Approved :: MIT License
Classifier: Operating System :: OS Independent
Classifier: Programming Language :: Python :: 3
Classifier: Programming Language :: Python :: 3.11
Classifier: Programming Language :: Python :: 3.12
Classifier: Topic :: Software Development :: Code Generators
Classifier: Topic :: Scientific/Engineering :: Artificial Intelligence
Classifier: Framework :: AWS CDK
Requires-Python: >=3.11
Requires-Dist: boto3>=1.34.0
Requires-Dist: google-generativeai>=0.3.0
Requires-Dist: pyyaml>=6.0
Requires-Dist: rich>=13.0.0
Requires-Dist: schedule>=1.2.0
Requires-Dist: pydantic>=2.5.0
Requires-Dist: httpx>=0.26.0
Provides-Extra: dev
Requires-Dist: pytest>=7.4.0; extra == "dev"
Requires-Dist: pytest-asyncio>=0.21.0; extra == "dev"
Requires-Dist: black>=23.0.0; extra == "dev"
Requires-Dist: ruff>=0.1.0; extra == "dev"
